FAIRtools/__init__.py
FAIRtools/collections.py
FAIRtools/evaluations.py
FAIRtools/metrics.py
FAIRtools/showup.py
FAIRtools-0.1.0.dist-info/METADATA
FAIRtools-0.1.0.dist-info/RECORD
FAIRtools-0.1.0.dist-info/WHEEL
FAIRtools-0.1.0.dist-info/top_level.txt
