Metadata-Version: 2.1
Name: FAIRtools
Version: 0.1.0
Summary: FAIR Metrics Evaluation Tool
Home-page: https://github.com/wilkinsonlab/FAIRtools
Author: Mario Prieto
Author-email: mario.prieto@upm.es
License: MIT license
Keywords: FAIRtools
Platform: UNKNOWN
Classifier: Development Status :: 2 - Pre-Alpha
Classifier: Intended Audience :: Developers
Classifier: License :: OSI Approved :: MIT License
Classifier: Natural Language :: English
Classifier: Programming Language :: Python :: 2
Classifier: Programming Language :: Python :: 2.7
Classifier: Programming Language :: Python :: 3
Classifier: Programming Language :: Python :: 3.4
Classifier: Programming Language :: Python :: 3.5
Classifier: Programming Language :: Python :: 3.6
Provides-Extra: dev
Requires-Dist: requests (==2.19.1)
Provides-Extra: dev
Requires-Dist: prospector[with_pyroma]; extra == 'dev'
Requires-Dist: yapf; extra == 'dev'
Requires-Dist: isort; extra == 'dev'
